<?xml version="1.0" encoding="UTF-8"?>
<objects serializationModel="Studio.02.02.00">
	<object class="AudioFile" id="{2f050f04-eb51-4b16-af80-7e776503a76b}">
		<property name="assetPath">
			<value>Puzzle 3 Dynamo Robotics Song.wav</value>
		</property>
		<property name="isStreaming">
			<value>true</value>
		</property>
		<property name="frequencyInKHz">
			<value>48</value>
		</property>
		<property name="channelCount">
			<value>2</value>
		</property>
		<property name="length">
			<value>234.30000000000001</value>
		</property>
		<relationship name="masterAssetFolder">
			<destination>{7c726035-5672-4201-9178-872899f50864}</destination>
		</relationship>
	</object>
</objects>
